<annotation>
	<folder></folder>
	<filename>biodegradable1784_jpeg.rf.00b81e0b8004a0a7c67b3c64dfb50cfc.jpg</filename>
	<path>biodegradable1784_jpeg.rf.00b81e0b8004a0a7c67b3c64dfb50cfc.jpg</path>
	<source>
		<database>roboflow.ai</database>
	</source>
	<size>
		<width>416</width>
		<height>416</height>
		<depth>3</depth>
	</size>
	<segmented>0</segmented>
	<object>
		<name>BIODEGRADABLE</name>
		<pose>Unspecified</pose>
		<truncated>0</truncated>
		<difficult>0</difficult>
		<occluded>0</occluded>
		<bndbox>
			<xmin>185</xmin>
			<xmax>415</xmax>
			<ymin>3</ymin>
			<ymax>149</ymax>
		</bndbox>
	</object>
	<object>
		<name>BIODEGRADABLE</name>
		<pose>Unspecified</pose>
		<truncated>0</truncated>
		<difficult>0</difficult>
		<occluded>0</occluded>
		<bndbox>
			<xmin>307</xmin>
			<xmax>415</xmax>
			<ymin>122</ymin>
			<ymax>242</ymax>
		</bndbox>
	</object>
	<object>
		<name>BIODEGRADABLE</name>
		<pose>Unspecified</pose>
		<truncated>0</truncated>
		<difficult>0</difficult>
		<occluded>0</occluded>
		<bndbox>
			<xmin>223</xmin>
			<xmax>383</xmax>
			<ymin>177</ymin>
			<ymax>330</ymax>
		</bndbox>
	</object>
	<object>
		<name>BIODEGRADABLE</name>
		<pose>Unspecified</pose>
		<truncated>0</truncated>
		<difficult>0</difficult>
		<occluded>0</occluded>
		<bndbox>
			<xmin>64</xmin>
			<xmax>284</xmax>
			<ymin>271</ymin>
			<ymax>417</ymax>
		</bndbox>
	</object>
	<object>
		<name>BIODEGRADABLE</name>
		<pose>Unspecified</pose>
		<truncated>0</truncated>
		<difficult>0</difficult>
		<occluded>0</occluded>
		<bndbox>
			<xmin>2</xmin>
			<xmax>286</xmax>
			<ymin>36</ymin>
			<ymax>272</ymax>
		</bndbox>
	</object>
	<object>
		<name>BIODEGRADABLE</name>
		<pose>Unspecified</pose>
		<truncated>0</truncated>
		<difficult>0</difficult>
		<occluded>0</occluded>
		<bndbox>
			<xmin>2</xmin>
			<xmax>12</xmax>
			<ymin>391</ymin>
			<ymax>416</ymax>
		</bndbox>
	</object>
	<object>
		<name>BIODEGRADABLE</name>
		<pose>Unspecified</pose>
		<truncated>0</truncated>
		<difficult>0</difficult>
		<occluded>0</occluded>
		<bndbox>
			<xmin>2</xmin>
			<xmax>200</xmax>
			<ymin>230</ymin>
			<ymax>416</ymax>
		</bndbox>
	</object>
</annotation>
