<annotation>
	<folder></folder>
	<filename>biodegradable66_jpg.rf.98f0a64083a666f1fad97ded97b5497f.jpg</filename>
	<path>biodegradable66_jpg.rf.98f0a64083a666f1fad97ded97b5497f.jpg</path>
	<source>
		<database>roboflow.ai</database>
	</source>
	<size>
		<width>416</width>
		<height>416</height>
		<depth>3</depth>
	</size>
	<segmented>0</segmented>
	<object>
		<name>BIODEGRADABLE</name>
		<pose>Unspecified</pose>
		<truncated>0</truncated>
		<difficult>0</difficult>
		<occluded>0</occluded>
		<bndbox>
			<xmin>156</xmin>
			<xmax>396</xmax>
			<ymin>187</ymin>
			<ymax>374</ymax>
		</bndbox>
	</object>
	<object>
		<name>BIODEGRADABLE</name>
		<pose>Unspecified</pose>
		<truncated>0</truncated>
		<difficult>0</difficult>
		<occluded>0</occluded>
		<bndbox>
			<xmin>45</xmin>
			<xmax>171</xmax>
			<ymin>136</ymin>
			<ymax>360</ymax>
		</bndbox>
	</object>
	<object>
		<name>BIODEGRADABLE</name>
		<pose>Unspecified</pose>
		<truncated>0</truncated>
		<difficult>0</difficult>
		<occluded>0</occluded>
		<bndbox>
			<xmin>154</xmin>
			<xmax>323</xmax>
			<ymin>130</ymin>
			<ymax>233</ymax>
		</bndbox>
	</object>
	<object>
		<name>BIODEGRADABLE</name>
		<pose>Unspecified</pose>
		<truncated>0</truncated>
		<difficult>0</difficult>
		<occluded>0</occluded>
		<bndbox>
			<xmin>71</xmin>
			<xmax>278</xmax>
			<ymin>36</ymin>
			<ymax>146</ymax>
		</bndbox>
	</object>
</annotation>
