<annotation>
	<folder></folder>
	<filename>biodegradable1626_jpg.rf.c2f0acb494cc320b064049d105a416cf.jpg</filename>
	<path>biodegradable1626_jpg.rf.c2f0acb494cc320b064049d105a416cf.jpg</path>
	<source>
		<database>roboflow.ai</database>
	</source>
	<size>
		<width>416</width>
		<height>416</height>
		<depth>3</depth>
	</size>
	<segmented>0</segmented>
	<object>
		<name>BIODEGRADABLE</name>
		<pose>Unspecified</pose>
		<truncated>0</truncated>
		<difficult>0</difficult>
		<occluded>0</occluded>
		<bndbox>
			<xmin>191</xmin>
			<xmax>257</xmax>
			<ymin>197</ymin>
			<ymax>247</ymax>
		</bndbox>
	</object>
	<object>
		<name>BIODEGRADABLE</name>
		<pose>Unspecified</pose>
		<truncated>0</truncated>
		<difficult>0</difficult>
		<occluded>0</occluded>
		<bndbox>
			<xmin>322</xmin>
			<xmax>360</xmax>
			<ymin>169</ymin>
			<ymax>256</ymax>
		</bndbox>
	</object>
	<object>
		<name>BIODEGRADABLE</name>
		<pose>Unspecified</pose>
		<truncated>0</truncated>
		<difficult>0</difficult>
		<occluded>0</occluded>
		<bndbox>
			<xmin>134</xmin>
			<xmax>208</xmax>
			<ymin>3</ymin>
			<ymax>94</ymax>
		</bndbox>
	</object>
	<object>
		<name>BIODEGRADABLE</name>
		<pose>Unspecified</pose>
		<truncated>0</truncated>
		<difficult>0</difficult>
		<occluded>0</occluded>
		<bndbox>
			<xmin>201</xmin>
			<xmax>268</xmax>
			<ymin>3</ymin>
			<ymax>69</ymax>
		</bndbox>
	</object>
	<object>
		<name>BIODEGRADABLE</name>
		<pose>Unspecified</pose>
		<truncated>0</truncated>
		<difficult>0</difficult>
		<occluded>0</occluded>
		<bndbox>
			<xmin>62</xmin>
			<xmax>138</xmax>
			<ymin>60</ymin>
			<ymax>199</ymax>
		</bndbox>
	</object>
	<object>
		<name>BIODEGRADABLE</name>
		<pose>Unspecified</pose>
		<truncated>0</truncated>
		<difficult>0</difficult>
		<occluded>0</occluded>
		<bndbox>
			<xmin>112</xmin>
			<xmax>142</xmax>
			<ymin>28</ymin>
			<ymax>69</ymax>
		</bndbox>
	</object>
	<object>
		<name>BIODEGRADABLE</name>
		<pose>Unspecified</pose>
		<truncated>0</truncated>
		<difficult>0</difficult>
		<occluded>0</occluded>
		<bndbox>
			<xmin>151</xmin>
			<xmax>211</xmax>
			<ymin>112</ymin>
			<ymax>174</ymax>
		</bndbox>
	</object>
	<object>
		<name>BIODEGRADABLE</name>
		<pose>Unspecified</pose>
		<truncated>0</truncated>
		<difficult>0</difficult>
		<occluded>0</occluded>
		<bndbox>
			<xmin>205</xmin>
			<xmax>267</xmax>
			<ymin>106</ymin>
			<ymax>154</ymax>
		</bndbox>
	</object>
	<object>
		<name>BIODEGRADABLE</name>
		<pose>Unspecified</pose>
		<truncated>0</truncated>
		<difficult>0</difficult>
		<occluded>0</occluded>
		<bndbox>
			<xmin>230</xmin>
			<xmax>274</xmax>
			<ymin>76</ymin>
			<ymax>124</ymax>
		</bndbox>
	</object>
	<object>
		<name>BIODEGRADABLE</name>
		<pose>Unspecified</pose>
		<truncated>0</truncated>
		<difficult>0</difficult>
		<occluded>0</occluded>
		<bndbox>
			<xmin>248</xmin>
			<xmax>322</xmax>
			<ymin>88</ymin>
			<ymax>156</ymax>
		</bndbox>
	</object>
	<object>
		<name>BIODEGRADABLE</name>
		<pose>Unspecified</pose>
		<truncated>0</truncated>
		<difficult>0</difficult>
		<occluded>0</occluded>
		<bndbox>
			<xmin>257</xmin>
			<xmax>340</xmax>
			<ymin>37</ymin>
			<ymax>117</ymax>
		</bndbox>
	</object>
	<object>
		<name>BIODEGRADABLE</name>
		<pose>Unspecified</pose>
		<truncated>0</truncated>
		<difficult>0</difficult>
		<occluded>0</occluded>
		<bndbox>
			<xmin>312</xmin>
			<xmax>360</xmax>
			<ymin>90</ymin>
			<ymax>213</ymax>
		</bndbox>
	</object>
	<object>
		<name>BIODEGRADABLE</name>
		<pose>Unspecified</pose>
		<truncated>0</truncated>
		<difficult>0</difficult>
		<occluded>0</occluded>
		<bndbox>
			<xmin>287</xmin>
			<xmax>365</xmax>
			<ymin>233</ymin>
			<ymax>342</ymax>
		</bndbox>
	</object>
	<object>
		<name>BIODEGRADABLE</name>
		<pose>Unspecified</pose>
		<truncated>0</truncated>
		<difficult>0</difficult>
		<occluded>0</occluded>
		<bndbox>
			<xmin>274</xmin>
			<xmax>298</xmax>
			<ymin>313</ymin>
			<ymax>345</ymax>
		</bndbox>
	</object>
	<object>
		<name>BIODEGRADABLE</name>
		<pose>Unspecified</pose>
		<truncated>0</truncated>
		<difficult>0</difficult>
		<occluded>0</occluded>
		<bndbox>
			<xmin>216</xmin>
			<xmax>298</xmax>
			<ymin>310</ymin>
			<ymax>360</ymax>
		</bndbox>
	</object>
	<object>
		<name>BIODEGRADABLE</name>
		<pose>Unspecified</pose>
		<truncated>0</truncated>
		<difficult>0</difficult>
		<occluded>0</occluded>
		<bndbox>
			<xmin>190</xmin>
			<xmax>236</xmax>
			<ymin>322</ymin>
			<ymax>404</ymax>
		</bndbox>
	</object>
	<object>
		<name>BIODEGRADABLE</name>
		<pose>Unspecified</pose>
		<truncated>0</truncated>
		<difficult>0</difficult>
		<occluded>0</occluded>
		<bndbox>
			<xmin>130</xmin>
			<xmax>206</xmax>
			<ymin>301</ymin>
			<ymax>408</ymax>
		</bndbox>
	</object>
	<object>
		<name>BIODEGRADABLE</name>
		<pose>Unspecified</pose>
		<truncated>0</truncated>
		<difficult>0</difficult>
		<occluded>0</occluded>
		<bndbox>
			<xmin>89</xmin>
			<xmax>136</xmax>
			<ymin>308</ymin>
			<ymax>394</ymax>
		</bndbox>
	</object>
	<object>
		<name>BIODEGRADABLE</name>
		<pose>Unspecified</pose>
		<truncated>0</truncated>
		<difficult>0</difficult>
		<occluded>0</occluded>
		<bndbox>
			<xmin>77</xmin>
			<xmax>153</xmax>
			<ymin>212</ymin>
			<ymax>324</ymax>
		</bndbox>
	</object>
	<object>
		<name>BIODEGRADABLE</name>
		<pose>Unspecified</pose>
		<truncated>0</truncated>
		<difficult>0</difficult>
		<occluded>0</occluded>
		<bndbox>
			<xmin>118</xmin>
			<xmax>156</xmax>
			<ymin>281</ymin>
			<ymax>313</ymax>
		</bndbox>
	</object>
	<object>
		<name>BIODEGRADABLE</name>
		<pose>Unspecified</pose>
		<truncated>0</truncated>
		<difficult>0</difficult>
		<occluded>0</occluded>
		<bndbox>
			<xmin>47</xmin>
			<xmax>130</xmax>
			<ymin>188</ymin>
			<ymax>297</ymax>
		</bndbox>
	</object>
	<object>
		<name>BIODEGRADABLE</name>
		<pose>Unspecified</pose>
		<truncated>0</truncated>
		<difficult>0</difficult>
		<occluded>0</occluded>
		<bndbox>
			<xmin>33</xmin>
			<xmax>80</xmax>
			<ymin>172</ymin>
			<ymax>236</ymax>
		</bndbox>
	</object>
	<object>
		<name>BIODEGRADABLE</name>
		<pose>Unspecified</pose>
		<truncated>0</truncated>
		<difficult>0</difficult>
		<occluded>0</occluded>
		<bndbox>
			<xmin>29</xmin>
			<xmax>360</xmax>
			<ymin>3</ymin>
			<ymax>416</ymax>
		</bndbox>
	</object>
	<object>
		<name>METAL</name>
		<pose>Unspecified</pose>
		<truncated>0</truncated>
		<difficult>0</difficult>
		<occluded>0</occluded>
		<bndbox>
			<xmin>219</xmin>
			<xmax>416</xmax>
			<ymin>212</ymin>
			<ymax>416</ymax>
		</bndbox>
	</object>
</annotation>
