<annotation>
	<folder></folder>
	<filename>cardboard248_jpg.rf.8b4e0fe1ddee5afc50bb4ecabfd275c4.jpg</filename>
	<path>cardboard248_jpg.rf.8b4e0fe1ddee5afc50bb4ecabfd275c4.jpg</path>
	<source>
		<database>roboflow.ai</database>
	</source>
	<size>
		<width>416</width>
		<height>416</height>
		<depth>3</depth>
	</size>
	<segmented>0</segmented>
	<object>
		<name>CARDBOARD</name>
		<pose>Unspecified</pose>
		<truncated>0</truncated>
		<difficult>0</difficult>
		<occluded>0</occluded>
		<bndbox>
			<xmin>2</xmin>
			<xmax>197</xmax>
			<ymin>2</ymin>
			<ymax>416</ymax>
		</bndbox>
	</object>
	<object>
		<name>CARDBOARD</name>
		<pose>Unspecified</pose>
		<truncated>0</truncated>
		<difficult>0</difficult>
		<occluded>0</occluded>
		<bndbox>
			<xmin>2</xmin>
			<xmax>340</xmax>
			<ymin>2</ymin>
			<ymax>416</ymax>
		</bndbox>
	</object>
</annotation>
