<annotation>
	<folder></folder>
	<filename>cardboard860_jpg.rf.066035ba233bf97a251bfcbe89cfcf95.jpg</filename>
	<path>cardboard860_jpg.rf.066035ba233bf97a251bfcbe89cfcf95.jpg</path>
	<source>
		<database>roboflow.ai</database>
	</source>
	<size>
		<width>416</width>
		<height>416</height>
		<depth>3</depth>
	</size>
	<segmented>0</segmented>
	<object>
		<name>CARDBOARD</name>
		<pose>Unspecified</pose>
		<truncated>0</truncated>
		<difficult>0</difficult>
		<occluded>0</occluded>
		<bndbox>
			<xmin>122</xmin>
			<xmax>311</xmax>
			<ymin>92</ymin>
			<ymax>324</ymax>
		</bndbox>
	</object>
</annotation>
