<annotation>
	<folder></folder>
	<filename>cardboard717_jpg.rf.93a6918f98c932edd97ef310113c08b8.jpg</filename>
	<path>cardboard717_jpg.rf.93a6918f98c932edd97ef310113c08b8.jpg</path>
	<source>
		<database>roboflow.ai</database>
	</source>
	<size>
		<width>416</width>
		<height>416</height>
		<depth>3</depth>
	</size>
	<segmented>0</segmented>
	<object>
		<name>CARDBOARD</name>
		<pose>Unspecified</pose>
		<truncated>0</truncated>
		<difficult>0</difficult>
		<occluded>0</occluded>
		<bndbox>
			<xmin>180</xmin>
			<xmax>333</xmax>
			<ymin>146</ymin>
			<ymax>349</ymax>
		</bndbox>
	</object>
	<object>
		<name>CARDBOARD</name>
		<pose>Unspecified</pose>
		<truncated>0</truncated>
		<difficult>0</difficult>
		<occluded>0</occluded>
		<bndbox>
			<xmin>238</xmin>
			<xmax>362</xmax>
			<ymin>29</ymin>
			<ymax>281</ymax>
		</bndbox>
	</object>
	<object>
		<name>CARDBOARD</name>
		<pose>Unspecified</pose>
		<truncated>0</truncated>
		<difficult>0</difficult>
		<occluded>0</occluded>
		<bndbox>
			<xmin>70</xmin>
			<xmax>239</xmax>
			<ymin>4</ymin>
			<ymax>266</ymax>
		</bndbox>
	</object>
	<object>
		<name>CARDBOARD</name>
		<pose>Unspecified</pose>
		<truncated>0</truncated>
		<difficult>0</difficult>
		<occluded>0</occluded>
		<bndbox>
			<xmin>44</xmin>
			<xmax>179</xmax>
			<ymin>91</ymin>
			<ymax>205</ymax>
		</bndbox>
	</object>
	<object>
		<name>CARDBOARD</name>
		<pose>Unspecified</pose>
		<truncated>0</truncated>
		<difficult>0</difficult>
		<occluded>0</occluded>
		<bndbox>
			<xmin>22</xmin>
			<xmax>169</xmax>
			<ymin>171</ymin>
			<ymax>349</ymax>
		</bndbox>
	</object>
	<object>
		<name>CARDBOARD</name>
		<pose>Unspecified</pose>
		<truncated>0</truncated>
		<difficult>0</difficult>
		<occluded>0</occluded>
		<bndbox>
			<xmin>1</xmin>
			<xmax>416</xmax>
			<ymin>1</ymin>
			<ymax>414</ymax>
		</bndbox>
	</object>
</annotation>
