<annotation>
	<folder></folder>
	<filename>cardboard5_jpg.rf.89933ab7c336f359ae06797d9d11155b.jpg</filename>
	<path>cardboard5_jpg.rf.89933ab7c336f359ae06797d9d11155b.jpg</path>
	<source>
		<database>roboflow.ai</database>
	</source>
	<size>
		<width>416</width>
		<height>416</height>
		<depth>3</depth>
	</size>
	<segmented>0</segmented>
	<object>
		<name>CARDBOARD</name>
		<pose>Unspecified</pose>
		<truncated>0</truncated>
		<difficult>0</difficult>
		<occluded>0</occluded>
		<bndbox>
			<xmin>45</xmin>
			<xmax>395</xmax>
			<ymin>1</ymin>
			<ymax>375</ymax>
		</bndbox>
	</object>
	<object>
		<name>CARDBOARD</name>
		<pose>Unspecified</pose>
		<truncated>0</truncated>
		<difficult>0</difficult>
		<occluded>0</occluded>
		<bndbox>
			<xmin>66</xmin>
			<xmax>370</xmax>
			<ymin>12</ymin>
			<ymax>288</ymax>
		</bndbox>
	</object>
	<object>
		<name>CARDBOARD</name>
		<pose>Unspecified</pose>
		<truncated>0</truncated>
		<difficult>0</difficult>
		<occluded>0</occluded>
		<bndbox>
			<xmin>22</xmin>
			<xmax>386</xmax>
			<ymin>27</ymin>
			<ymax>373</ymax>
		</bndbox>
	</object>
	<object>
		<name>CARDBOARD</name>
		<pose>Unspecified</pose>
		<truncated>0</truncated>
		<difficult>0</difficult>
		<occluded>0</occluded>
		<bndbox>
			<xmin>1</xmin>
			<xmax>416</xmax>
			<ymin>56</ymin>
			<ymax>416</ymax>
		</bndbox>
	</object>
</annotation>
