<annotation>
	<folder></folder>
	<filename>cardboard821_jpg.rf.0b367caef8d12ce73ea0c007b053ea25.jpg</filename>
	<path>cardboard821_jpg.rf.0b367caef8d12ce73ea0c007b053ea25.jpg</path>
	<source>
		<database>roboflow.ai</database>
	</source>
	<size>
		<width>416</width>
		<height>416</height>
		<depth>3</depth>
	</size>
	<segmented>0</segmented>
	<object>
		<name>CARDBOARD</name>
		<pose>Unspecified</pose>
		<truncated>0</truncated>
		<difficult>0</difficult>
		<occluded>0</occluded>
		<bndbox>
			<xmin>16</xmin>
			<xmax>397</xmax>
			<ymin>128</ymin>
			<ymax>308</ymax>
		</bndbox>
	</object>
</annotation>
