<annotation>
	<folder></folder>
	<filename>glass2726_jpg.rf.7f731bbc3b942ac3cd3425cdd98483ee.jpg</filename>
	<path>glass2726_jpg.rf.7f731bbc3b942ac3cd3425cdd98483ee.jpg</path>
	<source>
		<database>roboflow.ai</database>
	</source>
	<size>
		<width>416</width>
		<height>416</height>
		<depth>3</depth>
	</size>
	<segmented>0</segmented>
	<object>
		<name>GLASS</name>
		<pose>Unspecified</pose>
		<truncated>0</truncated>
		<difficult>0</difficult>
		<occluded>0</occluded>
		<bndbox>
			<xmin>42</xmin>
			<xmax>384</xmax>
			<ymin>94</ymin>
			<ymax>229</ymax>
		</bndbox>
	</object>
	<object>
		<name>GLASS</name>
		<pose>Unspecified</pose>
		<truncated>0</truncated>
		<difficult>0</difficult>
		<occluded>0</occluded>
		<bndbox>
			<xmin>6</xmin>
			<xmax>308</xmax>
			<ymin>295</ymin>
			<ymax>408</ymax>
		</bndbox>
	</object>
</annotation>
