<annotation>
	<folder></folder>
	<filename>glass1831_jpg.rf.afdafbaa7e0cc39e606bf19c34d122cb.jpg</filename>
	<path>glass1831_jpg.rf.afdafbaa7e0cc39e606bf19c34d122cb.jpg</path>
	<source>
		<database>roboflow.ai</database>
	</source>
	<size>
		<width>416</width>
		<height>416</height>
		<depth>3</depth>
	</size>
	<segmented>0</segmented>
	<object>
		<name>GLASS</name>
		<pose>Unspecified</pose>
		<truncated>0</truncated>
		<difficult>0</difficult>
		<occluded>0</occluded>
		<bndbox>
			<xmin>106</xmin>
			<xmax>190</xmax>
			<ymin>84</ymin>
			<ymax>285</ymax>
		</bndbox>
	</object>
	<object>
		<name>GLASS</name>
		<pose>Unspecified</pose>
		<truncated>0</truncated>
		<difficult>0</difficult>
		<occluded>0</occluded>
		<bndbox>
			<xmin>127</xmin>
			<xmax>264</xmax>
			<ymin>262</ymin>
			<ymax>318</ymax>
		</bndbox>
	</object>
	<object>
		<name>PLASTIC</name>
		<pose>Unspecified</pose>
		<truncated>0</truncated>
		<difficult>0</difficult>
		<occluded>0</occluded>
		<bndbox>
			<xmin>240</xmin>
			<xmax>329</xmax>
			<ymin>232</ymin>
			<ymax>289</ymax>
		</bndbox>
	</object>
</annotation>
