<annotation>
	<folder></folder>
	<filename>glass1032_jpg.rf.85b3e0138a113520f5a164ba98592f8d.jpg</filename>
	<path>glass1032_jpg.rf.85b3e0138a113520f5a164ba98592f8d.jpg</path>
	<source>
		<database>roboflow.ai</database>
	</source>
	<size>
		<width>416</width>
		<height>416</height>
		<depth>3</depth>
	</size>
	<segmented>0</segmented>
	<object>
		<name>GLASS</name>
		<pose>Unspecified</pose>
		<truncated>0</truncated>
		<difficult>0</difficult>
		<occluded>0</occluded>
		<bndbox>
			<xmin>39</xmin>
			<xmax>376</xmax>
			<ymin>131</ymin>
			<ymax>309</ymax>
		</bndbox>
	</object>
	<object>
		<name>METAL</name>
		<pose>Unspecified</pose>
		<truncated>0</truncated>
		<difficult>0</difficult>
		<occluded>0</occluded>
		<bndbox>
			<xmin>27</xmin>
			<xmax>52</xmax>
			<ymin>155</ymin>
			<ymax>197</ymax>
		</bndbox>
	</object>
</annotation>
