<annotation>
	<folder></folder>
	<filename>glass1086_jpg.rf.07f6dd4a6f0fc90ded03b5a00a976291.jpg</filename>
	<path>glass1086_jpg.rf.07f6dd4a6f0fc90ded03b5a00a976291.jpg</path>
	<source>
		<database>roboflow.ai</database>
	</source>
	<size>
		<width>416</width>
		<height>416</height>
		<depth>3</depth>
	</size>
	<segmented>0</segmented>
	<object>
		<name>GLASS</name>
		<pose>Unspecified</pose>
		<truncated>0</truncated>
		<difficult>0</difficult>
		<occluded>0</occluded>
		<bndbox>
			<xmin>150</xmin>
			<xmax>250</xmax>
			<ymin>71</ymin>
			<ymax>416</ymax>
		</bndbox>
	</object>
</annotation>
