<annotation>
	<folder></folder>
	<filename>glass517_jpg.rf.5535ed25653d64bf3496750e246d981c.jpg</filename>
	<path>glass517_jpg.rf.5535ed25653d64bf3496750e246d981c.jpg</path>
	<source>
		<database>roboflow.ai</database>
	</source>
	<size>
		<width>416</width>
		<height>416</height>
		<depth>3</depth>
	</size>
	<segmented>0</segmented>
	<object>
		<name>GLASS</name>
		<pose>Unspecified</pose>
		<truncated>0</truncated>
		<difficult>0</difficult>
		<occluded>0</occluded>
		<bndbox>
			<xmin>106</xmin>
			<xmax>313</xmax>
			<ymin>12</ymin>
			<ymax>416</ymax>
		</bndbox>
	</object>
	<object>
		<name>METAL</name>
		<pose>Unspecified</pose>
		<truncated>0</truncated>
		<difficult>0</difficult>
		<occluded>0</occluded>
		<bndbox>
			<xmin>165</xmin>
			<xmax>249</xmax>
			<ymin>2</ymin>
			<ymax>11</ymax>
		</bndbox>
	</object>
</annotation>
