<annotation>
	<folder></folder>
	<filename>metal728_jpg.rf.d199ed26dd6803b401a1fa3b550cea64.jpg</filename>
	<path>metal728_jpg.rf.d199ed26dd6803b401a1fa3b550cea64.jpg</path>
	<source>
		<database>roboflow.ai</database>
	</source>
	<size>
		<width>416</width>
		<height>416</height>
		<depth>3</depth>
	</size>
	<segmented>0</segmented>
	<object>
		<name>METAL</name>
		<pose>Unspecified</pose>
		<truncated>0</truncated>
		<difficult>0</difficult>
		<occluded>0</occluded>
		<bndbox>
			<xmin>155</xmin>
			<xmax>324</xmax>
			<ymin>57</ymin>
			<ymax>265</ymax>
		</bndbox>
	</object>
	<object>
		<name>METAL</name>
		<pose>Unspecified</pose>
		<truncated>0</truncated>
		<difficult>0</difficult>
		<occluded>0</occluded>
		<bndbox>
			<xmin>86</xmin>
			<xmax>215</xmax>
			<ymin>198</ymin>
			<ymax>340</ymax>
		</bndbox>
	</object>
</annotation>
