<annotation>
	<folder></folder>
	<filename>metal39_jpg.rf.80f4a99bc70dcb67ed7094f278a77900.jpg</filename>
	<path>metal39_jpg.rf.80f4a99bc70dcb67ed7094f278a77900.jpg</path>
	<source>
		<database>roboflow.ai</database>
	</source>
	<size>
		<width>416</width>
		<height>416</height>
		<depth>3</depth>
	</size>
	<segmented>0</segmented>
	<object>
		<name>METAL</name>
		<pose>Unspecified</pose>
		<truncated>0</truncated>
		<difficult>0</difficult>
		<occluded>0</occluded>
		<bndbox>
			<xmin>119</xmin>
			<xmax>269</xmax>
			<ymin>21</ymin>
			<ymax>208</ymax>
		</bndbox>
	</object>
	<object>
		<name>METAL</name>
		<pose>Unspecified</pose>
		<truncated>0</truncated>
		<difficult>0</difficult>
		<occluded>0</occluded>
		<bndbox>
			<xmin>210</xmin>
			<xmax>356</xmax>
			<ymin>191</ymin>
			<ymax>393</ymax>
		</bndbox>
	</object>
	<object>
		<name>METAL</name>
		<pose>Unspecified</pose>
		<truncated>0</truncated>
		<difficult>0</difficult>
		<occluded>0</occluded>
		<bndbox>
			<xmin>55</xmin>
			<xmax>203</xmax>
			<ymin>197</ymin>
			<ymax>395</ymax>
		</bndbox>
	</object>
</annotation>
