<annotation>
	<folder></folder>
	<filename>paper815_jpg.rf.f0240b4dce733e22ae8dd5835fa3df9f.jpg</filename>
	<path>paper815_jpg.rf.f0240b4dce733e22ae8dd5835fa3df9f.jpg</path>
	<source>
		<database>roboflow.ai</database>
	</source>
	<size>
		<width>416</width>
		<height>416</height>
		<depth>3</depth>
	</size>
	<segmented>0</segmented>
	<object>
		<name>PAPER</name>
		<pose>Unspecified</pose>
		<truncated>0</truncated>
		<difficult>0</difficult>
		<occluded>0</occluded>
		<bndbox>
			<xmin>3</xmin>
			<xmax>324</xmax>
			<ymin>1</ymin>
			<ymax>398</ymax>
		</bndbox>
	</object>
	<object>
		<name>PAPER</name>
		<pose>Unspecified</pose>
		<truncated>0</truncated>
		<difficult>0</difficult>
		<occluded>0</occluded>
		<bndbox>
			<xmin>124</xmin>
			<xmax>390</xmax>
			<ymin>106</ymin>
			<ymax>379</ymax>
		</bndbox>
	</object>
	<object>
		<name>PAPER</name>
		<pose>Unspecified</pose>
		<truncated>0</truncated>
		<difficult>0</difficult>
		<occluded>0</occluded>
		<bndbox>
			<xmin>1</xmin>
			<xmax>392</xmax>
			<ymin>1</ymin>
			<ymax>392</ymax>
		</bndbox>
	</object>
</annotation>
