<annotation>
	<folder></folder>
	<filename>paper1107_jpg.rf.f2687a282d9f33f4fd2c37eb2cc33732.jpg</filename>
	<path>paper1107_jpg.rf.f2687a282d9f33f4fd2c37eb2cc33732.jpg</path>
	<source>
		<database>roboflow.ai</database>
	</source>
	<size>
		<width>416</width>
		<height>416</height>
		<depth>3</depth>
	</size>
	<segmented>0</segmented>
	<object>
		<name>PAPER</name>
		<pose>Unspecified</pose>
		<truncated>0</truncated>
		<difficult>0</difficult>
		<occluded>0</occluded>
		<bndbox>
			<xmin>177</xmin>
			<xmax>373</xmax>
			<ymin>40</ymin>
			<ymax>349</ymax>
		</bndbox>
	</object>
	<object>
		<name>PAPER</name>
		<pose>Unspecified</pose>
		<truncated>0</truncated>
		<difficult>0</difficult>
		<occluded>0</occluded>
		<bndbox>
			<xmin>3</xmin>
			<xmax>205</xmax>
			<ymin>114</ymin>
			<ymax>299</ymax>
		</bndbox>
	</object>
</annotation>
