<annotation>
	<folder></folder>
	<filename>paper2208_jpg.rf.dc290307c0cb583caf614ec5de7917cf.jpg</filename>
	<path>paper2208_jpg.rf.dc290307c0cb583caf614ec5de7917cf.jpg</path>
	<source>
		<database>roboflow.ai</database>
	</source>
	<size>
		<width>416</width>
		<height>416</height>
		<depth>3</depth>
	</size>
	<segmented>0</segmented>
	<object>
		<name>PAPER</name>
		<pose>Unspecified</pose>
		<truncated>0</truncated>
		<difficult>0</difficult>
		<occluded>0</occluded>
		<bndbox>
			<xmin>1</xmin>
			<xmax>416</xmax>
			<ymin>68</ymin>
			<ymax>398</ymax>
		</bndbox>
	</object>
	<object>
		<name>PAPER</name>
		<pose>Unspecified</pose>
		<truncated>0</truncated>
		<difficult>0</difficult>
		<occluded>0</occluded>
		<bndbox>
			<xmin>2</xmin>
			<xmax>416</xmax>
			<ymin>37</ymin>
			<ymax>180</ymax>
		</bndbox>
	</object>
	<object>
		<name>PAPER</name>
		<pose>Unspecified</pose>
		<truncated>0</truncated>
		<difficult>0</difficult>
		<occluded>0</occluded>
		<bndbox>
			<xmin>50</xmin>
			<xmax>416</xmax>
			<ymin>2</ymin>
			<ymax>153</ymax>
		</bndbox>
	</object>
	<object>
		<name>PAPER</name>
		<pose>Unspecified</pose>
		<truncated>0</truncated>
		<difficult>0</difficult>
		<occluded>0</occluded>
		<bndbox>
			<xmin>1</xmin>
			<xmax>416</xmax>
			<ymin>2</ymin>
			<ymax>120</ymax>
		</bndbox>
	</object>
	<object>
		<name>PAPER</name>
		<pose>Unspecified</pose>
		<truncated>0</truncated>
		<difficult>0</difficult>
		<occluded>0</occluded>
		<bndbox>
			<xmin>322</xmin>
			<xmax>416</xmax>
			<ymin>2</ymin>
			<ymax>88</ymax>
		</bndbox>
	</object>
</annotation>
