<annotation>
	<folder></folder>
	<filename>paper1406_jpg.rf.04df6eea8974d727471181eca6d9fb5e.jpg</filename>
	<path>paper1406_jpg.rf.04df6eea8974d727471181eca6d9fb5e.jpg</path>
	<source>
		<database>roboflow.ai</database>
	</source>
	<size>
		<width>416</width>
		<height>416</height>
		<depth>3</depth>
	</size>
	<segmented>0</segmented>
	<object>
		<name>PAPER</name>
		<pose>Unspecified</pose>
		<truncated>0</truncated>
		<difficult>0</difficult>
		<occluded>0</occluded>
		<bndbox>
			<xmin>38</xmin>
			<xmax>270</xmax>
			<ymin>74</ymin>
			<ymax>416</ymax>
		</bndbox>
	</object>
	<object>
		<name>PAPER</name>
		<pose>Unspecified</pose>
		<truncated>0</truncated>
		<difficult>0</difficult>
		<occluded>0</occluded>
		<bndbox>
			<xmin>191</xmin>
			<xmax>412</xmax>
			<ymin>10</ymin>
			<ymax>349</ymax>
		</bndbox>
	</object>
	<object>
		<name>PAPER</name>
		<pose>Unspecified</pose>
		<truncated>0</truncated>
		<difficult>0</difficult>
		<occluded>0</occluded>
		<bndbox>
			<xmin>38</xmin>
			<xmax>413</xmax>
			<ymin>7</ymin>
			<ymax>416</ymax>
		</bndbox>
	</object>
</annotation>
