<annotation>
	<folder></folder>
	<filename>plastic595_jpg.rf.02423276a474e89ba14a2d1287b40fea.jpg</filename>
	<path>plastic595_jpg.rf.02423276a474e89ba14a2d1287b40fea.jpg</path>
	<source>
		<database>roboflow.ai</database>
	</source>
	<size>
		<width>416</width>
		<height>416</height>
		<depth>3</depth>
	</size>
	<segmented>0</segmented>
	<object>
		<name>PLASTIC</name>
		<pose>Unspecified</pose>
		<truncated>0</truncated>
		<difficult>0</difficult>
		<occluded>0</occluded>
		<bndbox>
			<xmin>69</xmin>
			<xmax>367</xmax>
			<ymin>112</ymin>
			<ymax>317</ymax>
		</bndbox>
	</object>
</annotation>
