<annotation>
	<folder></folder>
	<filename>plastic640_jpg.rf.d786b24b1a7ae60f9ab031ca68bf8765.jpg</filename>
	<path>plastic640_jpg.rf.d786b24b1a7ae60f9ab031ca68bf8765.jpg</path>
	<source>
		<database>roboflow.ai</database>
	</source>
	<size>
		<width>416</width>
		<height>416</height>
		<depth>3</depth>
	</size>
	<segmented>0</segmented>
	<object>
		<name>PLASTIC</name>
		<pose>Unspecified</pose>
		<truncated>0</truncated>
		<difficult>0</difficult>
		<occluded>0</occluded>
		<bndbox>
			<xmin>139</xmin>
			<xmax>273</xmax>
			<ymin>28</ymin>
			<ymax>388</ymax>
		</bndbox>
	</object>
	<object>
		<name>PLASTIC</name>
		<pose>Unspecified</pose>
		<truncated>0</truncated>
		<difficult>0</difficult>
		<occluded>0</occluded>
		<bndbox>
			<xmin>184</xmin>
			<xmax>228</xmax>
			<ymin>28</ymin>
			<ymax>54</ymax>
		</bndbox>
	</object>
</annotation>
