<annotation>
	<folder></folder>
	<filename>plastic74_jpg.rf.6c46ceaeda3d5420efaa07df5d635625.jpg</filename>
	<path>plastic74_jpg.rf.6c46ceaeda3d5420efaa07df5d635625.jpg</path>
	<source>
		<database>roboflow.ai</database>
	</source>
	<size>
		<width>416</width>
		<height>416</height>
		<depth>3</depth>
	</size>
	<segmented>0</segmented>
	<object>
		<name>PLASTIC</name>
		<pose>Unspecified</pose>
		<truncated>0</truncated>
		<difficult>0</difficult>
		<occluded>0</occluded>
		<bndbox>
			<xmin>136</xmin>
			<xmax>304</xmax>
			<ymin>25</ymin>
			<ymax>343</ymax>
		</bndbox>
	</object>
	<object>
		<name>PLASTIC</name>
		<pose>Unspecified</pose>
		<truncated>0</truncated>
		<difficult>0</difficult>
		<occluded>0</occluded>
		<bndbox>
			<xmin>69</xmin>
			<xmax>263</xmax>
			<ymin>6</ymin>
			<ymax>372</ymax>
		</bndbox>
	</object>
	<object>
		<name>PLASTIC</name>
		<pose>Unspecified</pose>
		<truncated>0</truncated>
		<difficult>0</difficult>
		<occluded>0</occluded>
		<bndbox>
			<xmin>141</xmin>
			<xmax>268</xmax>
			<ymin>10</ymin>
			<ymax>188</ymax>
		</bndbox>
	</object>
	<object>
		<name>PLASTIC</name>
		<pose>Unspecified</pose>
		<truncated>0</truncated>
		<difficult>0</difficult>
		<occluded>0</occluded>
		<bndbox>
			<xmin>120</xmin>
			<xmax>250</xmax>
			<ymin>10</ymin>
			<ymax>242</ymax>
		</bndbox>
	</object>
</annotation>
